{
  "video_name": "2024-02-14_20-37-55",
  "video_path": "data/video/2024-02-14_20-37-55.mp4",
  "pixel_points": [
    [
      185,
      353
    ],
    [
      187,
      563
    ],
    [
      410,
      348
    ],
    [
      410,
      562
    ],
    [
      640,
      344
    ],
    [
      640,
      560
    ],
    [
      977,
      340
    ],
    [
      975,
      560
    ],
    [
      1346,
      339
    ],
    [
      1345,
      560
    ],
    [
      1580,
      341
    ],
    [
      1579,
      558
    ],
    [
      1809,
      343
    ],
    [
      1808,
      557
    ],
    [
      313,
      488
    ],
    [
      542,
      486
    ],
    [
      773,
      487
    ],
    [
      1142,
      487
    ],
    [
      1481,
      484
    ],
    [
      1713,
      485
    ]
  ],
  "point_count": 20,
  "description": "웹 도구로 수집된 픽셀 좌표"
}