{
  "video_name": "2024-09-05_21-13-49",
  "video_path": "data/video/2024-09-05_21-13-49.mp4",
  "pixel_points": [
    [
      302,
      441
    ],
    [
      300,
      595
    ],
    [
      489,
      439
    ],
    [
      485,
      596
    ],
    [
      672,
      439
    ],
    [
      672,
      600
    ],
    [
      947,
      439
    ],
    [
      947,
      597
    ],
    [
      1246,
      439
    ],
    [
      1244,
      600
    ],
    [
      1438,
      441
    ],
    [
      1437,
      602
    ],
    [
      1621,
      442
    ],
    [
      1623,
      601
    ],
    [
      404,
      537
    ],
    [
      591,
      538
    ],
    [
      780,
      537
    ],
    [
      1083,
      537
    ],
    [
      1356,
      540
    ],
    [
      1544,
      540
    ]
  ],
  "point_count": 20,
  "description": "웹 도구로 수집된 픽셀 좌표"
}